3 stage Pipeline implementation/code.v
module pipeline (a,b,c,d,clk,f);
    parameter n=10;
    input[n-1:0]a,b,c,d;
    output[n-1:0]f;
    input clk;
    reg[n-1:0]l12_x1,l12_x2,l12_d,l23_x3,l23_d,l34_f;
    assign f = l34_f;
    always @(posedge clk) begin
        #4 l12_x1 <= a+b;
        #4 l12_x2 <= c-d;
        l12_d <= d;
    end
    always @(posedge clk) begin
        #4 l23_x3 <= l12_x1+l12_x2;
        l23_d <= l12_d;
        
    end
    always @(posedge clk) begin
        #6 l34_f <= l23_x3 * l23_d;
        
    end
    

endmodule

3 stage Pipeline implementation/testbench.v
module pipetest;
parameter n=10;
reg[n-1:0]a,b,c,d;
reg clk;
wire[n-1:0]f;
pipeline dut(.c(c), .a(a), .b(b), .d(d), .f(f), .clk(clk));
initial begin
    clk = 1'b0;
    a=0; b=0; c=0; d=0; 
end
always #10 clk = ~clk;
initial begin
    #5 a=10; b=12; c=6; d=3; 
    #20 a=10; b=10; c=5; d=3; 
    #20 a=20; b=11; c=1; d=4; 
    #20 a=15; b=10; c=8; d=2; 
    #20 a=8; b=15; c=5; d=0; 
    #20 a=10; b=20; c=5; d=3; 
    #20 a=30; b=1; c=2; d=4; 
end

initial begin
    $dumpfile("pipe.vcd");
    $dumpvars(0,pipetest);
    $monitor("time: %d, f = %h",$time,f);
    #300 $finish;
end
endmodule

3 stage Pipeline implementation/pipe.vcd
$date
	Wed Sep 17 23:44:31 2025
$end
$version
	Icarus Verilog
$end
$timescale
	1s
$end
$scope module pipetest $end
$var wire 10 ! f [9:0] $end
$var reg 10 " a [9:0] $end
$var reg 10 # b [9:0] $end
$var reg 10 $ c [9:0] $end
$var reg 1 % clk $end
$var reg 10 & d [9:0] $end
$scope module dut $end
$var wire 10 ' a [9:0] $end
$var wire 10 ( b [9:0] $end
$var wire 10 ) c [9:0] $end
$var wire 1 * clk $end
$var wire 10 + d [9:0] $end
$var wire 10 , f [9:0] $end
$var reg 10 - l12_d [9:0] $end
$var reg 10 . l12_x1 [9:0] $end
$var reg 10 / l12_x2 [9:0] $end
$var reg 10 0 l23_d [9:0] $end
$var reg 10 1 l23_x3 [9:0] $end
$var reg 10 2 l34_f [9:0] $end
$upscope $end
$upscope $end
$enddefinitions $end
#0
$dumpvars
bx 2
bx 1
bx 0
bx /
bx .
bx -
bx ,
b0 +
0*
b0 )
b0 (
b0 '
b0 &
0%
b0 $
b0 #
b0 "
bx !
$end
#5
b11 &
b11 +
b110 $
b110 )
b1100 #
b1100 (
b1010 "
b1010 '
#10
1%
1*
#14
b10110 .
#18
b11 -
b11 /
#20
0%
0*
#25
b101 $
b101 )
b1010 #
b1010 (
#30
1%
1*
#34
b11 0
b11001 1
b10100 .
#36
b1001011 2
b1001011 !
b1001011 ,
#38
b10 /
#40
0%
0*
#45
b100 &
b100 +
b1 $
b1 )
b1011 #
b1011 (
b10100 "
b10100 '
#50
1%
1*
#54
b10110 1
b11111 .
#56
b1000010 2
b1000010 !
b1000010 ,
#58
b100 -
b1111111101 /
#60
0%
0*
#65
b10 &
b10 +
b1000 $
b1000 )
b1010 #
b1010 (
b1111 "
b1111 '
#70
1%
1*
#74
b100 0
b11100 1
b11001 .
#76
b1110000 2
b1110000 !
b1110000 ,
#78
b10 -
b110 /
#80
0%
0*
#85
b0 &
b0 +
b101 $
b101 )
b1111 #
b1111 (
b1000 "
b1000 '
#90
1%
1*
#94
b10 0
b11111 1
b10111 .
#96
b111110 2
b111110 !
b111110 ,
#98
b0 -
b101 /
#100
0%
0*
#105
b11 &
b11 +
b10100 #
b10100 (
b1010 "
b1010 '
#110
1%
1*
#114
b0 0
b11100 1
b11110 .
#116
b0 2
b0 !
b0 ,
#118
b11 -
b10 /
#120
0%
0*
#125
b100 &
b100 +
b10 $
b10 )
b1 #
b1 (
b11110 "
b11110 '
#130
1%
1*
#134
b11 0
b100000 1
b11111 .
#136
b1100000 2
b1100000 !
b1100000 ,
#138
b100 -
b1111111110 /
#140
0%
0*
#150
1%
1*
#154
b100 0
b11101 1
#156
b1110100 2
b1110100 !
b1110100 ,
