Parity Generator/parity_gen.v
module parity(x,z,clk);
    input x,clk;
    output reg z;
    parameter even=0,odd=1;
    reg even_odd;
    always@(posedge clk)
        begin
            case (even_odd)
                even:begin
                        z<=x?1:0;
                        even_odd <= x?odd:even;
                    end
                odd:begin
                        z<=x?0:1;
                        even_odd <= x?even:odd;
                    end
                default: even_odd<=even;
            endcase
        end

endmodule

Parity Generator/parity_tb.v
module parity_tb;
reg x,clk;
wire z;
parity dut(.x(x), .clk(clk), .z(z));
initial begin
    $dumpfile("parity.vcd");
    $dumpvars(0,parity_tb);
    clk = 1'b0;
end
always #5 clk = ~clk;
initial 
    begin
        #2 x=0; #10 x=1; #10 x=1;
        #10 x=0; #10 x=1;
        #10 x=0; #10 x=0;#10 x=1; #10 x=0;
        #30 $finish;
    end
endmodule

Parity Generator/parity.vcd
$date
	Sat Sep 06 21:27:29 2025
$end
$version
	Icarus Verilog
$end
$timescale
	1s
$end
$scope module parity_tb $end
$var wire 1 ! z $end
$var reg 1 " clk $end
$var reg 1 # x $end
$scope module dut $end
$var wire 1 $ clk $end
$var wire 1 % x $end
$var reg 1 & even_odd $end
$var reg 1 ' z $end
$upscope $end
$upscope $end
$enddefinitions $end
#0
$dumpvars
x'
x&
x%
0$
x#
0"
x!
$end
#2
0#
0%
#5
0&
1"
1$
#10
0"
0$
#12
1#
1%
#15
1&
1'
1!
1"
1$
#20
0"
0$
#25
0&
0'
0!
1"
1$
#30
0"
0$
#32
0#
0%
#35
1"
1$
#40
0"
0$
#42
1#
1%
#45
1&
1'
1!
1"
1$
#50
0"
0$
#52
0#
0%
#55
1"
1$
#60
0"
0$
#65
1"
1$
#70
0"
0$
#72
1#
1%
#75
0&
0'
0!
1"
1$
#80
0"
0$
#82
0#
0%
